{
  "name": "round-007-right-p-screen",
  "candidate_label": "right-p=83.527052",
  "wheel_scores": {
    "left": {
      "wheel": "left",
      "sample_count": 15,
      "mean_abs_error": 18.2,
      "p95_abs_error": 30.599999999999998,
      "overshoot_peak": 32.0,
      "settle_delay_s": 1.2115,
      "pwm_settle_delay_s": 1.22225,
      "saturation_ratio": 0.06666666666666667,
      "steady_abs_error_ratio": 0.1925925925925926,
      "p95_error_ratio": 0.3191666666666666,
      "settle_time_ratio": 1.0,
      "pwm_settle_time_ratio": 1.0,
      "overshoot_ratio": 0.17777777777777778,
      "oscillation_ratio": 0.05052278638290966,
      "attainment_ratio": 0.8074074074074075,
      "rail_hit_ratio": 0.0,
      "pwm_chatter_ratio": 0.0,
      "tail_mean_abs_error": 18.0,
      "tail_pwm_jump_abs": 1068.0833333333333,
      "terminal_requirements_ok": false,
      "pwm_limit_reasonable": false,
      "pwm_limit_note": "terminal steady-state gate failed (tail error or PWM jump exceeded limits)",
      "weighted_score": Infinity
    },
    "right": {
      "wheel": "right",
      "sample_count": 15,
      "mean_abs_error": 16.533333333333335,
      "p95_abs_error": 24.199999999999996,
      "overshoot_peak": 2.0,
      "settle_delay_s": 1.2115,
      "pwm_settle_delay_s": 1.22225,
      "saturation_ratio": 0.0,
      "steady_abs_error_ratio": 0.21666666666666667,
      "p95_error_ratio": 0.2672222222222222,
      "settle_time_ratio": 1.0,
      "pwm_settle_time_ratio": 1.0,
      "overshoot_ratio": 0.011111111111111112,
      "oscillation_ratio": 0.04604287751353274,
      "attainment_ratio": 0.7833333333333333,
      "rail_hit_ratio": 0.0,
      "pwm_chatter_ratio": 0.0,
      "tail_mean_abs_error": 19.083333333333332,
      "tail_pwm_jump_abs": 826.5833333333334,
      "terminal_requirements_ok": false,
      "pwm_limit_reasonable": false,
      "pwm_limit_note": "terminal steady-state gate failed (tail error or PWM jump exceeded limits)",
      "weighted_score": Infinity
    }
  },
  "csv_path": "/home/madejuele/projects/2K0300/new/verification/auto-wheel-pid/20260422T154816Z/round-007-right-p-screen/attempt-01/telemetry.csv",
  "host_log_path": "/home/madejuele/projects/2K0300/new/verification/auto-wheel-pid/20260422T154816Z/round-007-right-p-screen/attempt-01/host.log",
  "board_log_path": "/home/madejuele/projects/2K0300/new/verification/auto-wheel-pid/20260422T154816Z/round-007-right-p-screen/attempt-01/board.log",
  "params_path": "/home/madejuele/projects/2K0300/new/verification/auto-wheel-pid/20260422T154816Z/round-007-right-p-screen/attempt-01/params.json",
  "tuning_exit_code": 0,
  "receiver_error": null,
  "ack_complete": true,
  "snapshot_cleared_seen": true,
  "board_markers_ok": true,
  "unexpected_failsafe": false,
  "runtime_error": null,
  "accepted": false,
  "accepted_reason": "screen right terminal gate failed: tail error 19.083 > 2.000; tail PWM jump 826.583 > 500.000"
}
