{
  "name": "baseline-screen",
  "candidate_label": "current-working-params-screen",
  "wheel_scores": {
    "left": {
      "wheel": "left",
      "sample_count": 21,
      "mean_abs_error": 16.333333333333332,
      "p95_abs_error": 21.0,
      "overshoot_peak": 0.0,
      "settle_delay_s": 1.2650000000000001,
      "pwm_settle_delay_s": 0.9268095238095237,
      "saturation_ratio": 0.0,
      "steady_abs_error_ratio": 0.15343915343915346,
      "p95_error_ratio": 0.19428571428571428,
      "settle_time_ratio": 1.0,
      "pwm_settle_time_ratio": 0.7304882310020657,
      "overshoot_ratio": 0.0,
      "oscillation_ratio": 0.018928594964283448,
      "attainment_ratio": 0.8465608465608466,
      "rail_hit_ratio": 0.0,
      "pwm_chatter_ratio": 0.0,
      "tail_mean_abs_error": 16.49206349206349,
      "tail_pwm_jump_abs": 355.23809523809524,
      "terminal_requirements_ok": true,
      "pwm_limit_reasonable": true,
      "pwm_limit_note": "within current wheel-PID test envelope",
      "weighted_score": 1.3379531197857628
    },
    "right": {
      "wheel": "right",
      "sample_count": 21,
      "mean_abs_error": 18.571428571428573,
      "p95_abs_error": 30.0,
      "overshoot_peak": 0.0,
      "settle_delay_s": 1.2650000000000001,
      "pwm_settle_delay_s": 1.265666666666667,
      "saturation_ratio": 0.09523809523809523,
      "steady_abs_error_ratio": 0.17989417989417988,
      "p95_error_ratio": 0.2577777777777777,
      "settle_time_ratio": 1.0,
      "pwm_settle_time_ratio": 1.0,
      "overshoot_ratio": 0.0,
      "oscillation_ratio": 0.0559379693459061,
      "attainment_ratio": 0.8201058201058202,
      "rail_hit_ratio": 0.047619047619047616,
      "pwm_chatter_ratio": 0.0,
      "tail_mean_abs_error": 18.444444444444443,
      "tail_pwm_jump_abs": 1087.1904761904761,
      "terminal_requirements_ok": false,
      "pwm_limit_reasonable": false,
      "pwm_limit_note": "terminal steady-state gate failed (tail error or PWM jump exceeded limits)",
      "weighted_score": Infinity
    }
  },
  "csv_path": "/home/madejuele/projects/2K0300/new/verification/auto-wheel-pid/20260423T111801Z/baseline-screen/attempt-01/telemetry.csv",
  "host_log_path": "/home/madejuele/projects/2K0300/new/verification/auto-wheel-pid/20260423T111801Z/baseline-screen/attempt-01/host.log",
  "board_log_path": "/home/madejuele/projects/2K0300/new/verification/auto-wheel-pid/20260423T111801Z/baseline-screen/attempt-01/board.log",
  "params_path": "/home/madejuele/projects/2K0300/new/verification/auto-wheel-pid/20260423T111801Z/baseline-screen/attempt-01/params.json",
  "tuning_exit_code": 0,
  "receiver_error": null,
  "ack_complete": true,
  "snapshot_cleared_seen": true,
  "board_markers_ok": true,
  "unexpected_failsafe": false,
  "runtime_error": null,
  "accepted": true,
  "accepted_reason": "baseline-screen"
}
