{
  "name": "round-024-right-d",
  "candidate_label": "right-d=0.100000",
  "wheel_scores": {
    "left": {
      "wheel": "left",
      "sample_count": 69,
      "mean_abs_error": 28.695652173913043,
      "p95_abs_error": 40.0,
      "overshoot_peak": 0.0,
      "settle_delay_s": 1.5585,
      "pwm_settle_delay_s": 0.9878883248730965,
      "saturation_ratio": 0.0,
      "steady_abs_error_ratio": 0.6065989847715736,
      "p95_error_ratio": 0.682741116751269,
      "settle_time_ratio": 1.0,
      "pwm_settle_time_ratio": 0.6172760790178138,
      "overshoot_ratio": 0.0,
      "oscillation_ratio": 0.05561716509412385,
      "attainment_ratio": 0.3934010152284264,
      "rail_hit_ratio": 0.0,
      "pwm_chatter_ratio": 0.0,
      "tail_mean_abs_error": 30.81979695431472,
      "tail_pwm_jump_abs": 323.4517766497462,
      "terminal_requirements_ok": false,
      "pwm_limit_reasonable": false,
      "pwm_limit_note": "terminal steady-state gate failed (tail error or PWM jump exceeded limits)",
      "weighted_score": Infinity
    },
    "right": {
      "wheel": "right",
      "sample_count": 69,
      "mean_abs_error": 34.130434782608695,
      "p95_abs_error": 50.19999999999999,
      "overshoot_peak": 0.0,
      "settle_delay_s": 1.5585,
      "pwm_settle_delay_s": 0.9635380710659899,
      "saturation_ratio": 0.0,
      "steady_abs_error_ratio": 0.6734348561759729,
      "p95_error_ratio": 0.8106598984771572,
      "settle_time_ratio": 1.0,
      "pwm_settle_time_ratio": 0.5991382144881426,
      "overshoot_ratio": 0.0,
      "oscillation_ratio": 0.0665442268775344,
      "attainment_ratio": 0.32656514382402707,
      "rail_hit_ratio": 0.0,
      "pwm_chatter_ratio": 0.0,
      "tail_mean_abs_error": 35.50592216582064,
      "tail_pwm_jump_abs": 320.26395939086296,
      "terminal_requirements_ok": false,
      "pwm_limit_reasonable": false,
      "pwm_limit_note": "terminal steady-state gate failed (tail error or PWM jump exceeded limits)",
      "weighted_score": Infinity
    }
  },
  "csv_path": "/home/madejuele/projects/2K0300/new/verification/auto-wheel-pid/20260422T121437Z/round-024-right-d/attempt-01/telemetry.csv",
  "host_log_path": "/home/madejuele/projects/2K0300/new/verification/auto-wheel-pid/20260422T121437Z/round-024-right-d/attempt-01/host.log",
  "board_log_path": "/home/madejuele/projects/2K0300/new/verification/auto-wheel-pid/20260422T121437Z/round-024-right-d/attempt-01/board.log",
  "params_path": "/home/madejuele/projects/2K0300/new/verification/auto-wheel-pid/20260422T121437Z/round-024-right-d/attempt-01/params.json",
  "tuning_exit_code": 0,
  "receiver_error": null,
  "ack_complete": true,
  "snapshot_cleared_seen": true,
  "board_markers_ok": true,
  "unexpected_failsafe": false,
  "runtime_error": null,
  "accepted": false,
  "accepted_reason": "right score 27.416917 did not beat 25.706435 by 5%"
}
